awsssoreporting/__init__.py
awsssoreporting/__main__.py
awsssoreporting-0.12.dist-info/LICENSE
awsssoreporting-0.12.dist-info/METADATA
awsssoreporting-0.12.dist-info/WHEEL
awsssoreporting-0.12.dist-info/entry_points.txt
awsssoreporting-0.12.dist-info/top_level.txt
awsssoreporting-0.12.dist-info/RECORD
