Metadata-Version: 2.1
Name: awsssoreporting
Version: 0.12
Summary: This tool will report on identities and access in AWS IAM Identity Center
Author-email: Jeff Maley <jeffmaley@gmail.com>
License: # MIT License
Project-URL: Homepage, https://github.com/jeffmaley/awsssoreporting
Project-URL: Bug Tracker, https://github.com/jeffmaley/awsssoreporting/issues
Classifier: Programming Language :: Python :: 3
Classifier: License :: OSI Approved :: MIT License
Classifier: Operating System :: OS Independent
Requires-Python: >=3.7
License-File: LICENSE
Requires-Dist: boto3
